python_artifact_signer/__init__.py
python_artifact_signer/main.py
python_artifact_signer/merkle_proof.py
python_artifact_signer/util.py
python_artifact_signer-0.5.0.dist-info/METADATA
python_artifact_signer-0.5.0.dist-info/WHEEL
python_artifact_signer-0.5.0.dist-info/entry_points.txt
python_artifact_signer-0.5.0.dist-info/RECORD
